{"name":"Sweetie_Bunny","power":"https://emotion.xiaokang.me/","common":[],"all":[{"name":"12311678","url":"https://7.dusays.com/2021/01/15/7dbd6cb091434.png"},{"name":"12311679","url":"https://7.dusays.com/2021/01/15/7dd3ebfd5e4f2.png"},{"name":"12311680","url":"https://7.dusays.com/2021/01/15/8d595099e5681.png"},{"name":"12311681","url":"https://7.dusays.com/2021/01/15/ae048b7becd4a.png"},{"name":"12311682","url":"https://7.dusays.com/2021/01/15/5cea88bc03823.png"},{"name":"12311683","url":"https://7.dusays.com/2021/01/15/bb366541200e9.png"},{"name":"12311684","url":"https://7.dusays.com/2021/01/15/8d894e50b36a4.png"},{"name":"12311685","url":"https://7.dusays.com/2021/01/15/4cea0a581e748.png"},{"name":"12311686","url":"https://7.dusays.com/2021/01/15/8a6445177bcc0.png"},{"name":"12311687","url":"https://7.dusays.com/2021/01/15/60f52a91235bb.png"},{"name":"12311688","url":"https://7.dusays.com/2021/01/15/af0c609d5dc8c.png"},{"name":"12311689","url":"https://7.dusays.com/2021/01/15/0c14a64751bc5.png"},{"name":"12311690","url":"https://7.dusays.com/2021/01/15/baff72cbd24a9.png"},{"name":"12311691","url":"https://7.dusays.com/2021/01/15/9d75a973b614e.png"},{"name":"12311692","url":"https://7.dusays.com/2021/01/15/783216af81325.png"},{"name":"12311693","url":"https://7.dusays.com/2021/01/15/ed1a4b374cc72.png"},{"name":"12311694","url":"https://7.dusays.com/2021/01/15/2b0591a64a193.png"},{"name":"12311695","url":"https://7.dusays.com/2021/01/15/c2bdbe596b74d.png"},{"name":"12311696","url":"https://7.dusays.com/2021/01/15/7851ab343b20d.png"},{"name":"12311697","url":"https://7.dusays.com/2021/01/15/d3af514158645.png"},{"name":"12311698","url":"https://7.dusays.com/2021/01/15/7e5f401262505.png"},{"name":"12311699","url":"https://7.dusays.com/2021/01/15/ffd66f2dff20e.png"},{"name":"12311700","url":"https://7.dusays.com/2021/01/15/80816287d7f1c.png"},{"name":"12311701","url":"https://7.dusays.com/2021/01/15/675c4055ab461.png"},{"name":"12311702","url":"https://7.dusays.com/2021/01/15/ed1d96cb7f768.png"},{"name":"12311703","url":"https://7.dusays.com/2021/01/15/67e18db6de8c5.png"},{"name":"12311704","url":"https://7.dusays.com/2021/01/15/9021d9e976f33.png"},{"name":"12311705","url":"https://7.dusays.com/2021/01/15/83293220b2e34.png"},{"name":"12311706","url":"https://7.dusays.com/2021/01/15/b4c7dcb5c1ca6.png"},{"name":"12311707","url":"https://7.dusays.com/2021/01/15/0492e05b433c2.png"},{"name":"12311708","url":"https://7.dusays.com/2021/01/15/27c55f50dad38.png"},{"name":"12311709","url":"https://7.dusays.com/2021/01/15/78466ae8a59bd.png"},{"name":"12311710","url":"https://7.dusays.com/2021/01/15/55e1a4b5b3cd2.png"},{"name":"12311711","url":"https://7.dusays.com/2021/01/15/688e14c7ccfa5.png"},{"name":"12311712","url":"https://7.dusays.com/2021/01/15/7a9eb76579f19.png"},{"name":"12311713","url":"https://7.dusays.com/2021/01/15/e11c3ddf34976.png"},{"name":"12311714","url":"https://7.dusays.com/2021/01/15/a424a764bbd2a.png"},{"name":"12311715","url":"https://7.dusays.com/2021/01/15/e268beb35825c.png"},{"name":"12311716","url":"https://7.dusays.com/2021/01/15/f56b29552083a.png"},{"name":"12311717","url":"https://7.dusays.com/2021/01/15/c73d96badb472.png"}]}
