{"name":"恶搞QQ","power":"https://emotion.xiaokang.me/","common":[],"all":[{"name":"1","url":"https://bu.dusays.com/2021/01/15/60df04aba9b8d.gif"},{"name":"10","url":"https://bu.dusays.com/2021/01/15/bbdcf84af0d40.png"},{"name":"100","url":"https://bu.dusays.com/2021/01/15/adc9d9aa58956.gif"},{"name":"101","url":"https://bu.dusays.com/2021/01/15/00369b2295809.gif"},{"name":"102","url":"https://bu.dusays.com/2021/01/15/d28f5cf4db397.gif"},{"name":"103","url":"https://bu.dusays.com/2021/01/15/e6ff9967fa080.gif"},{"name":"104","url":"https://bu.dusays.com/2021/01/15/c2f0d31c0899e.gif"},{"name":"105","url":"https://bu.dusays.com/2021/01/15/da00d77da660e.gif"},{"name":"106","url":"https://bu.dusays.com/2021/01/15/cb925f1ce242c.gif"},{"name":"107","url":"https://bu.dusays.com/2021/01/15/62cd5578b5b92.gif"},{"name":"108","url":"https://bu.dusays.com/2021/01/15/f944f7c47a03c.gif"},{"name":"109","url":"https://bu.dusays.com/2021/01/15/f31138e55af56.jpg"},{"name":"11","url":"https://bu.dusays.com/2021/01/15/50609a96e8555.gif"},{"name":"110","url":"https://bu.dusays.com/2021/01/15/7ca79691d1fdf.gif"},{"name":"111","url":"https://bu.dusays.com/2021/01/15/7d89e5a903f29.gif"},{"name":"112","url":"https://bu.dusays.com/2021/01/15/80d7b30ff78d6.gif"},{"name":"113","url":"https://bu.dusays.com/2021/01/15/01d78d6fee512.gif"},{"name":"114","url":"https://bu.dusays.com/2021/01/15/db34772511147.gif"},{"name":"115","url":"https://bu.dusays.com/2021/01/15/e12aae4fd31a2.gif"},{"name":"116","url":"https://bu.dusays.com/2021/01/15/ac20ad23ea70e.gif"},{"name":"117","url":"https://bu.dusays.com/2021/01/15/f24ca7308435c.gif"},{"name":"118","url":"https://bu.dusays.com/2021/01/15/ba69911513445.gif"},{"name":"119","url":"https://bu.dusays.com/2021/01/15/fd24043cc9f03.gif"},{"name":"12","url":"https://bu.dusays.com/2021/01/15/456b2187b1c9d.png"},{"name":"120","url":"https://bu.dusays.com/2021/01/15/03e43eb40f653.gif"},{"name":"121","url":"https://bu.dusays.com/2021/01/15/af154ce7e837d.gif"},{"name":"122","url":"https://bu.dusays.com/2021/01/15/37ddca94bf313.gif"},{"name":"123","url":"https://bu.dusays.com/2021/01/15/37faeaac70d4e.gif"},{"name":"124","url":"https://bu.dusays.com/2021/01/15/f1432f01da8d4.gif"},{"name":"125","url":"https://bu.dusays.com/2021/01/15/865b9f24ee28e.gif"},{"name":"126","url":"https://bu.dusays.com/2021/01/15/56eb3101b3b8d.gif"},{"name":"127","url":"https://bu.dusays.com/2021/01/15/977fd87742858.gif"},{"name":"128","url":"https://bu.dusays.com/2021/01/15/76486037619e3.gif"},{"name":"129","url":"https://bu.dusays.com/2021/01/15/1349730a0e7f2.gif"},{"name":"13","url":"https://bu.dusays.com/2021/01/15/254a40c1b5335.gif"},{"name":"130","url":"https://bu.dusays.com/2021/01/15/5fddcd5d3772b.gif"},{"name":"131","url":"https://bu.dusays.com/2021/01/15/050e51277a624.gif"},{"name":"132","url":"https://bu.dusays.com/2021/01/15/7a4f7f4130a52.gif"},{"name":"133","url":"https://bu.dusays.com/2021/01/15/a6a9866ca72f5.jpg"},{"name":"134","url":"https://bu.dusays.com/2021/01/15/ea894665f5c82.gif"},{"name":"135","url":"https://bu.dusays.com/2021/01/15/6d741ed79ecce.gif"},{"name":"136","url":"https://bu.dusays.com/2021/01/15/dc224392f4074.gif"},{"name":"137","url":"https://bu.dusays.com/2021/01/15/98070f9c711f3.gif"},{"name":"138","url":"https://bu.dusays.com/2021/01/15/5478b1deffe74.gif"},{"name":"139","url":"https://bu.dusays.com/2021/01/15/9bd45a2952d44.gif"},{"name":"14","url":"https://bu.dusays.com/2021/01/15/7f67b0398242c.gif"},{"name":"140","url":"https://bu.dusays.com/2021/01/15/03cd5bdb84d59.gif"},{"name":"141","url":"https://bu.dusays.com/2021/01/15/8610af3883f2a.gif"},{"name":"142","url":"https://bu.dusays.com/2021/01/15/b4f7b4e81b75f.gif"},{"name":"143","url":"https://bu.dusays.com/2021/01/15/3e7ab44234cc4.gif"},{"name":"144","url":"https://bu.dusays.com/2021/01/15/fba1f067e58be.gif"},{"name":"145","url":"https://bu.dusays.com/2021/01/15/218f1ef3def6b.gif"},{"name":"146","url":"https://bu.dusays.com/2021/01/15/97fa576b7daef.gif"},{"name":"147","url":"https://bu.dusays.com/2021/01/15/043a7a99b2c2b.gif"},{"name":"148","url":"https://bu.dusays.com/2021/01/15/626625a78e5e0.gif"},{"name":"149","url":"https://bu.dusays.com/2021/01/15/54ffa7abe7347.gif"},{"name":"15","url":"https://bu.dusays.com/2021/01/15/10289b7b0cedd.gif"},{"name":"150","url":"https://bu.dusays.com/2021/01/15/f7febc55fb089.gif"},{"name":"151","url":"https://bu.dusays.com/2021/01/15/4d5ffca869725.gif"},{"name":"152","url":"https://bu.dusays.com/2021/01/15/8e12c00bb1d2e.png"},{"name":"153","url":"https://bu.dusays.com/2021/01/15/f36258bac378c.gif"},{"name":"154","url":"https://bu.dusays.com/2021/01/15/552f55b5cf3f5.gif"},{"name":"155","url":"https://bu.dusays.com/2021/01/15/037157d4918c5.gif"},{"name":"156","url":"https://bu.dusays.com/2021/01/15/83f1c8a483efc.gif"},{"name":"157","url":"https://bu.dusays.com/2021/01/15/37d66c12c3690.gif"},{"name":"158","url":"https://bu.dusays.com/2021/01/15/9127627e7d407.jpg"},{"name":"159","url":"https://bu.dusays.com/2021/01/15/75d3136d6dca2.gif"},{"name":"16","url":"https://bu.dusays.com/2021/01/15/30453cd3548f7.gif"},{"name":"160","url":"https://bu.dusays.com/2021/01/15/da6ab2742b64e.gif"},{"name":"161","url":"https://bu.dusays.com/2021/01/15/f7717e019311a.gif"},{"name":"162","url":"https://bu.dusays.com/2021/01/15/210b385ba9ba1.gif"},{"name":"163","url":"https://bu.dusays.com/2021/01/15/892528301d24e.gif"},{"name":"164","url":"https://bu.dusays.com/2021/01/15/1c04eab4461cc.gif"},{"name":"165","url":"https://bu.dusays.com/2021/01/15/d77686d8af355.gif"},{"name":"166","url":"https://bu.dusays.com/2021/01/15/aa6c700dd4e4d.gif"},{"name":"167","url":"https://bu.dusays.com/2021/01/15/f44bd3063e059.gif"},{"name":"168","url":"https://bu.dusays.com/2021/01/15/57c4238e4ba82.gif"},{"name":"169","url":"https://bu.dusays.com/2021/01/15/b76f0839a9476.gif"},{"name":"17","url":"https://bu.dusays.com/2021/01/15/f50e8d0a5472e.gif"},{"name":"170","url":"https://bu.dusays.com/2021/01/15/760578091322f.gif"},{"name":"171","url":"https://bu.dusays.com/2021/01/15/53b7554973ef2.gif"},{"name":"172","url":"https://bu.dusays.com/2021/01/15/1d42f0e5adb03.gif"},{"name":"173","url":"https://bu.dusays.com/2021/01/15/cd18531381b96.gif"},{"name":"174","url":"https://bu.dusays.com/2021/01/15/e8d59bf157f5f.gif"},{"name":"175","url":"https://bu.dusays.com/2021/01/15/cf6efa19ed356.gif"},{"name":"176","url":"https://bu.dusays.com/2021/01/15/2562391c7f8a7.gif"},{"name":"177","url":"https://bu.dusays.com/2021/01/15/eee5b3c411463.gif"},{"name":"178","url":"https://bu.dusays.com/2021/01/15/eabe5971223fc.gif"},{"name":"179","url":"https://bu.dusays.com/2021/01/15/45bc7a4678e30.gif"},{"name":"18","url":"https://bu.dusays.com/2021/01/15/c365ecc2efb8f.gif"},{"name":"180","url":"https://bu.dusays.com/2021/01/15/1892d3ce00f1d.gif"},{"name":"19","url":"https://bu.dusays.com/2021/01/15/f72a4e01f4262.gif"},{"name":"2","url":"https://bu.dusays.com/2021/01/15/ba523a8132cc5.gif"},{"name":"20","url":"https://bu.dusays.com/2021/01/15/1d5113bf9c598.gif"},{"name":"21","url":"https://bu.dusays.com/2021/01/15/c68454bfbda82.gif"},{"name":"22","url":"https://bu.dusays.com/2021/01/15/15e839d07f411.gif"},{"name":"23","url":"https://bu.dusays.com/2021/01/15/c16e4f9942185.gif"},{"name":"24","url":"https://bu.dusays.com/2021/01/15/1dab470838c2d.gif"},{"name":"25","url":"https://bu.dusays.com/2021/01/15/10c47cbae100c.gif"},{"name":"26","url":"https://bu.dusays.com/2021/01/15/32c39130de4ce.gif"},{"name":"27","url":"https://bu.dusays.com/2021/01/15/c018b8f0f4080.gif"},{"name":"28","url":"https://bu.dusays.com/2021/01/15/63887595e54f9.gif"},{"name":"29","url":"https://bu.dusays.com/2021/01/15/512c334e79c71.gif"},{"name":"3","url":"https://bu.dusays.com/2021/01/15/eeb9bda6f793c.gif"},{"name":"30","url":"https://bu.dusays.com/2021/01/15/a327d96392e10.gif"},{"name":"31","url":"https://bu.dusays.com/2021/01/15/31ca9f45c8025.gif"},{"name":"32","url":"https://bu.dusays.com/2021/01/15/30768689b4512.gif"},{"name":"33","url":"https://bu.dusays.com/2021/01/15/8ebb135b50e63.gif"},{"name":"34","url":"https://bu.dusays.com/2021/01/15/c6a9550e09d22.gif"},{"name":"35","url":"https://bu.dusays.com/2021/01/15/6e99b54708601.gif"},{"name":"36","url":"https://bu.dusays.com/2021/01/15/6b7cdbf1a71d9.gif"},{"name":"37","url":"https://bu.dusays.com/2021/01/15/e5056dac90db0.gif"},{"name":"38","url":"https://bu.dusays.com/2021/01/15/f7a8249479745.gif"},{"name":"39","url":"https://bu.dusays.com/2021/01/15/114b948a1b875.gif"},{"name":"4","url":"https://bu.dusays.com/2021/01/15/b31ee822c70b9.gif"},{"name":"40","url":"https://bu.dusays.com/2021/01/15/bfe71d53b5261.gif"},{"name":"41","url":"https://bu.dusays.com/2021/01/15/54b5109c55318.gif"},{"name":"42","url":"https://bu.dusays.com/2021/01/15/bd12097e2be8c.gif"},{"name":"43","url":"https://bu.dusays.com/2021/01/15/17a2a30481cc2.gif"},{"name":"44","url":"https://bu.dusays.com/2021/01/15/414aec5ee1ff9.gif"},{"name":"45","url":"https://bu.dusays.com/2021/01/15/af95f4e6b9582.gif"},{"name":"46","url":"https://bu.dusays.com/2021/01/15/0c3da240d442d.gif"},{"name":"47","url":"https://bu.dusays.com/2021/01/15/2fea508fe035d.gif"},{"name":"48","url":"https://bu.dusays.com/2021/01/15/3aa8f327fafda.gif"},{"name":"49","url":"https://bu.dusays.com/2021/01/15/d3836e792052f.gif"},{"name":"5","url":"https://bu.dusays.com/2021/01/15/5c03d15e01dff.gif"},{"name":"50","url":"https://bu.dusays.com/2021/01/15/694aedfccce09.gif"},{"name":"51","url":"https://bu.dusays.com/2021/01/15/245f88890d0fc.jpg"},{"name":"52","url":"https://bu.dusays.com/2021/01/15/25186df4377a7.gif"},{"name":"53","url":"https://bu.dusays.com/2021/01/15/98ce8a5ff2196.gif"},{"name":"54","url":"https://bu.dusays.com/2021/01/15/66559aa9507d5.gif"},{"name":"55","url":"https://bu.dusays.com/2021/01/15/7286b69cdc4e0.jpg"},{"name":"56","url":"https://bu.dusays.com/2021/01/15/caa9ae98b781e.gif"},{"name":"57","url":"https://bu.dusays.com/2021/01/15/8fed1cf6b3650.gif"},{"name":"58","url":"https://bu.dusays.com/2021/01/15/22b68e484ee27.gif"},{"name":"59","url":"https://bu.dusays.com/2021/01/15/f36cdd295c179.gif"},{"name":"6","url":"https://bu.dusays.com/2021/01/15/e38a414034e80.gif"},{"name":"60","url":"https://bu.dusays.com/2021/01/15/9aaf1f3147bc7.gif"},{"name":"61","url":"https://bu.dusays.com/2021/01/15/9f741573a66ec.gif"},{"name":"62","url":"https://bu.dusays.com/2021/01/15/fda3d80b01d81.gif"},{"name":"63","url":"https://bu.dusays.com/2021/01/15/c165d07be8377.gif"},{"name":"64","url":"https://bu.dusays.com/2021/01/15/cadb712a16ae7.gif"},{"name":"65","url":"https://bu.dusays.com/2021/01/15/9dcb6ffa0914e.jpg"},{"name":"66","url":"https://bu.dusays.com/2021/01/15/db5522677fb0f.gif"},{"name":"67","url":"https://bu.dusays.com/2021/01/15/d867fd474adb7.gif"},{"name":"68","url":"https://bu.dusays.com/2021/01/15/59f55ec50a496.gif"},{"name":"69","url":"https://bu.dusays.com/2021/01/15/427dc804bdddb.gif"},{"name":"7","url":"https://bu.dusays.com/2021/01/15/1d543c52af39d.gif"},{"name":"70","url":"https://bu.dusays.com/2021/01/15/cd147567d8a18.gif"},{"name":"71","url":"https://bu.dusays.com/2021/01/15/a6aec0818e09f.gif"},{"name":"72","url":"https://bu.dusays.com/2021/01/15/a8e145c8fe186.gif"},{"name":"73","url":"https://bu.dusays.com/2021/01/15/461995e17cf5e.gif"},{"name":"74","url":"https://bu.dusays.com/2021/01/15/caf6e351646f9.gif"},{"name":"75","url":"https://bu.dusays.com/2021/01/15/25fb70fff3ef7.jpg"},{"name":"76","url":"https://bu.dusays.com/2021/01/15/b07518af6a54a.gif"},{"name":"77","url":"https://bu.dusays.com/2021/01/15/2db063916c54e.gif"},{"name":"78","url":"https://bu.dusays.com/2021/01/15/73695c83ff6aa.gif"},{"name":"79","url":"https://bu.dusays.com/2021/01/15/2dec58c1429ac.gif"},{"name":"8","url":"https://bu.dusays.com/2021/01/15/6cd26dd4ab732.gif"},{"name":"80","url":"https://bu.dusays.com/2021/01/15/eb4781a9308d9.gif"},{"name":"81","url":"https://bu.dusays.com/2021/01/15/128c28821be60.jpg"},{"name":"82","url":"https://bu.dusays.com/2021/01/15/9c031226b3079.gif"},{"name":"83","url":"https://bu.dusays.com/2021/01/15/e48867016f3f0.gif"},{"name":"84","url":"https://bu.dusays.com/2021/01/15/661147a659ea3.gif"},{"name":"85","url":"https://bu.dusays.com/2021/01/15/880d927b3ef67.gif"},{"name":"86","url":"https://bu.dusays.com/2021/01/15/e1af3c0304ee5.gif"},{"name":"87","url":"https://bu.dusays.com/2021/01/15/11ea6716d4d27.gif"},{"name":"88","url":"https://bu.dusays.com/2021/01/15/4214d4be9e88d.gif"},{"name":"89","url":"https://bu.dusays.com/2021/01/15/77b52dc7cda74.gif"},{"name":"9","url":"https://bu.dusays.com/2021/01/15/89ef41d40d11e.gif"},{"name":"90","url":"https://bu.dusays.com/2021/01/15/e8715d0f4d833.gif"},{"name":"91","url":"https://bu.dusays.com/2021/01/15/731f57614fde5.gif"},{"name":"92","url":"https://bu.dusays.com/2021/01/15/c7bb342e1dc23.gif"},{"name":"93","url":"https://bu.dusays.com/2021/01/15/f477e08938f8d.gif"},{"name":"94","url":"https://bu.dusays.com/2021/01/15/5c02da0237d88.gif"},{"name":"95","url":"https://bu.dusays.com/2021/01/15/4e4dd01862dee.gif"},{"name":"96","url":"https://bu.dusays.com/2021/01/15/2c2e982031af0.jpg"},{"name":"97","url":"https://bu.dusays.com/2021/01/15/58491c0827875.gif"},{"name":"98","url":"https://bu.dusays.com/2021/01/15/d0cf30b0db42d.gif"},{"name":"99","url":"https://bu.dusays.com/2021/01/15/6ea01cadfbd46.gif"}]}
