{"common":[],"all":[{"name":"01","url":"https://cdn.jsdelivr.net/gh/Dreamy-TZK/iemotion-pic@latest/img/气泡熊/01.gif"},{"name":"02","url":"https://cdn.jsdelivr.net/gh/Dreamy-TZK/iemotion-pic@latest/img/气泡熊/02.gif"},{"name":"03","url":"https://cdn.jsdelivr.net/gh/Dreamy-TZK/iemotion-pic@latest/img/气泡熊/03.gif"},{"name":"04","url":"https://cdn.jsdelivr.net/gh/Dreamy-TZK/iemotion-pic@latest/img/气泡熊/04.gif"},{"name":"05","url":"https://cdn.jsdelivr.net/gh/Dreamy-TZK/iemotion-pic@latest/img/气泡熊/05.gif"},{"name":"06","url":"https://cdn.jsdelivr.net/gh/Dreamy-TZK/iemotion-pic@latest/img/气泡熊/06.gif"},{"name":"07","url":"https://cdn.jsdelivr.net/gh/Dreamy-TZK/iemotion-pic@latest/img/气泡熊/07.gif"},{"name":"08","url":"https://cdn.jsdelivr.net/gh/Dreamy-TZK/iemotion-pic@latest/img/气泡熊/08.gif"},{"name":"09","url":"https://cdn.jsdelivr.net/gh/Dreamy-TZK/iemotion-pic@latest/img/气泡熊/09.gif"},{"name":"10","url":"https://cdn.jsdelivr.net/gh/Dreamy-TZK/iemotion-pic@latest/img/气泡熊/10.gif"},{"name":"11","url":"https://cdn.jsdelivr.net/gh/Dreamy-TZK/iemotion-pic@latest/img/气泡熊/11.gif"},{"name":"12","url":"https://cdn.jsdelivr.net/gh/Dreamy-TZK/iemotion-pic@latest/img/气泡熊/12.gif"},{"name":"13","url":"https://cdn.jsdelivr.net/gh/Dreamy-TZK/iemotion-pic@latest/img/气泡熊/13.gif"},{"name":"14","url":"https://cdn.jsdelivr.net/gh/Dreamy-TZK/iemotion-pic@latest/img/气泡熊/14.gif"},{"name":"15","url":"https://cdn.jsdelivr.net/gh/Dreamy-TZK/iemotion-pic@latest/img/气泡熊/15.gif"},{"name":"16","url":"https://cdn.jsdelivr.net/gh/Dreamy-TZK/iemotion-pic@latest/img/气泡熊/16.gif"},{"name":"17","url":"https://cdn.jsdelivr.net/gh/Dreamy-TZK/iemotion-pic@latest/img/气泡熊/17.gif"},{"name":"18","url":"https://cdn.jsdelivr.net/gh/Dreamy-TZK/iemotion-pic@latest/img/气泡熊/18.gif"},{"name":"19","url":"https://cdn.jsdelivr.net/gh/Dreamy-TZK/iemotion-pic@latest/img/气泡熊/19.gif"},{"name":"20","url":"https://cdn.jsdelivr.net/gh/Dreamy-TZK/iemotion-pic@latest/img/气泡熊/20.gif"},{"name":"21","url":"https://cdn.jsdelivr.net/gh/Dreamy-TZK/iemotion-pic@latest/img/气泡熊/21.gif"},{"name":"22","url":"https://cdn.jsdelivr.net/gh/Dreamy-TZK/iemotion-pic@latest/img/气泡熊/22.gif"},{"name":"23","url":"https://cdn.jsdelivr.net/gh/Dreamy-TZK/iemotion-pic@latest/img/气泡熊/23.gif"},{"name":"24","url":"https://cdn.jsdelivr.net/gh/Dreamy-TZK/iemotion-pic@latest/img/气泡熊/24.gif"},{"name":"25","url":"https://cdn.jsdelivr.net/gh/Dreamy-TZK/iemotion-pic@latest/img/气泡熊/25.gif"},{"name":"26","url":"https://cdn.jsdelivr.net/gh/Dreamy-TZK/iemotion-pic@latest/img/气泡熊/26.gif"},{"name":"27","url":"https://cdn.jsdelivr.net/gh/Dreamy-TZK/iemotion-pic@latest/img/气泡熊/27.gif"},{"name":"28","url":"https://cdn.jsdelivr.net/gh/Dreamy-TZK/iemotion-pic@latest/img/气泡熊/28.gif"},{"name":"29","url":"https://cdn.jsdelivr.net/gh/Dreamy-TZK/iemotion-pic@latest/img/气泡熊/29.gif"},{"name":"30","url":"https://cdn.jsdelivr.net/gh/Dreamy-TZK/iemotion-pic@latest/img/气泡熊/30.gif"},{"name":"31","url":"https://cdn.jsdelivr.net/gh/Dreamy-TZK/iemotion-pic@latest/img/气泡熊/31.gif"},{"name":"32","url":"https://cdn.jsdelivr.net/gh/Dreamy-TZK/iemotion-pic@latest/img/气泡熊/32.gif"},{"name":"33","url":"https://cdn.jsdelivr.net/gh/Dreamy-TZK/iemotion-pic@latest/img/气泡熊/33.gif"},{"name":"34","url":"https://cdn.jsdelivr.net/gh/Dreamy-TZK/iemotion-pic@latest/img/气泡熊/34.gif"},{"name":"35","url":"https://cdn.jsdelivr.net/gh/Dreamy-TZK/iemotion-pic@latest/img/气泡熊/35.gif"},{"name":"36","url":"https://cdn.jsdelivr.net/gh/Dreamy-TZK/iemotion-pic@latest/img/气泡熊/36.gif"},{"name":"37","url":"https://cdn.jsdelivr.net/gh/Dreamy-TZK/iemotion-pic@latest/img/气泡熊/37.gif"},{"name":"38","url":"https://cdn.jsdelivr.net/gh/Dreamy-TZK/iemotion-pic@latest/img/气泡熊/38.gif"},{"name":"39","url":"https://cdn.jsdelivr.net/gh/Dreamy-TZK/iemotion-pic@latest/img/气泡熊/39.gif"},{"name":"40","url":"https://cdn.jsdelivr.net/gh/Dreamy-TZK/iemotion-pic@latest/img/气泡熊/40.gif"},{"name":"41","url":"https://cdn.jsdelivr.net/gh/Dreamy-TZK/iemotion-pic@latest/img/气泡熊/41.gif"},{"name":"42","url":"https://cdn.jsdelivr.net/gh/Dreamy-TZK/iemotion-pic@latest/img/气泡熊/42.gif"},{"name":"43","url":"https://cdn.jsdelivr.net/gh/Dreamy-TZK/iemotion-pic@latest/img/气泡熊/43.gif"},{"name":"44","url":"https://cdn.jsdelivr.net/gh/Dreamy-TZK/iemotion-pic@latest/img/气泡熊/44.gif"},{"name":"45","url":"https://cdn.jsdelivr.net/gh/Dreamy-TZK/iemotion-pic@latest/img/气泡熊/45.gif"},{"name":"46","url":"https://cdn.jsdelivr.net/gh/Dreamy-TZK/iemotion-pic@latest/img/气泡熊/46.gif"},{"name":"47","url":"https://cdn.jsdelivr.net/gh/Dreamy-TZK/iemotion-pic@latest/img/气泡熊/47.gif"},{"name":"48","url":"https://cdn.jsdelivr.net/gh/Dreamy-TZK/iemotion-pic@latest/img/气泡熊/48.gif"},{"name":"49","url":"https://cdn.jsdelivr.net/gh/Dreamy-TZK/iemotion-pic@latest/img/气泡熊/49.gif"},{"name":"50","url":"https://cdn.jsdelivr.net/gh/Dreamy-TZK/iemotion-pic@latest/img/气泡熊/50.gif"},{"name":"51","url":"https://cdn.jsdelivr.net/gh/Dreamy-TZK/iemotion-pic@latest/img/气泡熊/51.gif"},{"name":"52","url":"https://cdn.jsdelivr.net/gh/Dreamy-TZK/iemotion-pic@latest/img/气泡熊/52.gif"},{"name":"53","url":"https://cdn.jsdelivr.net/gh/Dreamy-TZK/iemotion-pic@latest/img/气泡熊/53.gif"},{"name":"54","url":"https://cdn.jsdelivr.net/gh/Dreamy-TZK/iemotion-pic@latest/img/气泡熊/54.gif"},{"name":"55","url":"https://cdn.jsdelivr.net/gh/Dreamy-TZK/iemotion-pic@latest/img/气泡熊/55.gif"},{"name":"56","url":"https://cdn.jsdelivr.net/gh/Dreamy-TZK/iemotion-pic@latest/img/气泡熊/56.gif"},{"name":"57","url":"https://cdn.jsdelivr.net/gh/Dreamy-TZK/iemotion-pic@latest/img/气泡熊/57.gif"},{"name":"58","url":"https://cdn.jsdelivr.net/gh/Dreamy-TZK/iemotion-pic@latest/img/气泡熊/58.gif"},{"name":"59","url":"https://cdn.jsdelivr.net/gh/Dreamy-TZK/iemotion-pic@latest/img/气泡熊/59.gif"},{"name":"60","url":"https://cdn.jsdelivr.net/gh/Dreamy-TZK/iemotion-pic@latest/img/气泡熊/60.gif"},{"name":"61","url":"https://cdn.jsdelivr.net/gh/Dreamy-TZK/iemotion-pic@latest/img/气泡熊/61.gif"},{"name":"62","url":"https://cdn.jsdelivr.net/gh/Dreamy-TZK/iemotion-pic@latest/img/气泡熊/62.gif"}]}