{"name":"猥琐萌","power":"https://emotion.xiaokang.me/","common":[],"all":[{"name":"1","url":"https://cdn.jsdelivr.net/gh/Dreamy-TZK/iemotion-pic@latest/img/猥琐萌/1.jpg"},{"name":"10","url":"https://cdn.jsdelivr.net/gh/Dreamy-TZK/iemotion-pic@latest/img/猥琐萌/10.jpg"},{"name":"100","url":"https://cdn.jsdelivr.net/gh/Dreamy-TZK/iemotion-pic@latest/img/猥琐萌/100.jpg"},{"name":"101","url":"https://cdn.jsdelivr.net/gh/Dreamy-TZK/iemotion-pic@latest/img/猥琐萌/101.jpg"},{"name":"102","url":"https://cdn.jsdelivr.net/gh/Dreamy-TZK/iemotion-pic@latest/img/猥琐萌/102.jpg"},{"name":"103","url":"https://cdn.jsdelivr.net/gh/Dreamy-TZK/iemotion-pic@latest/img/猥琐萌/103.jpg"},{"name":"104","url":"https://cdn.jsdelivr.net/gh/Dreamy-TZK/iemotion-pic@latest/img/猥琐萌/104.jpg"},{"name":"105","url":"https://cdn.jsdelivr.net/gh/Dreamy-TZK/iemotion-pic@latest/img/猥琐萌/105.jpg"},{"name":"106","url":"https://cdn.jsdelivr.net/gh/Dreamy-TZK/iemotion-pic@latest/img/猥琐萌/106.jpg"},{"name":"107","url":"https://cdn.jsdelivr.net/gh/Dreamy-TZK/iemotion-pic@latest/img/猥琐萌/107.jpg"},{"name":"108","url":"https://cdn.jsdelivr.net/gh/Dreamy-TZK/iemotion-pic@latest/img/猥琐萌/108.jpg"},{"name":"109","url":"https://cdn.jsdelivr.net/gh/Dreamy-TZK/iemotion-pic@latest/img/猥琐萌/109.jpg"},{"name":"11","url":"https://cdn.jsdelivr.net/gh/Dreamy-TZK/iemotion-pic@latest/img/猥琐萌/11.jpg"},{"name":"110","url":"https://cdn.jsdelivr.net/gh/Dreamy-TZK/iemotion-pic@latest/img/猥琐萌/110.jpg"},{"name":"111","url":"https://cdn.jsdelivr.net/gh/Dreamy-TZK/iemotion-pic@latest/img/猥琐萌/111.jpg"},{"name":"112","url":"https://cdn.jsdelivr.net/gh/Dreamy-TZK/iemotion-pic@latest/img/猥琐萌/112.jpg"},{"name":"113","url":"https://cdn.jsdelivr.net/gh/Dreamy-TZK/iemotion-pic@latest/img/猥琐萌/113.jpg"},{"name":"114","url":"https://cdn.jsdelivr.net/gh/Dreamy-TZK/iemotion-pic@latest/img/猥琐萌/114.jpg"},{"name":"115","url":"https://cdn.jsdelivr.net/gh/Dreamy-TZK/iemotion-pic@latest/img/猥琐萌/115.jpg"},{"name":"116","url":"https://cdn.jsdelivr.net/gh/Dreamy-TZK/iemotion-pic@latest/img/猥琐萌/116.jpg"},{"name":"117","url":"https://cdn.jsdelivr.net/gh/Dreamy-TZK/iemotion-pic@latest/img/猥琐萌/117.jpg"},{"name":"118","url":"https://cdn.jsdelivr.net/gh/Dreamy-TZK/iemotion-pic@latest/img/猥琐萌/118.jpg"},{"name":"119","url":"https://cdn.jsdelivr.net/gh/Dreamy-TZK/iemotion-pic@latest/img/猥琐萌/119.jpg"},{"name":"12","url":"https://cdn.jsdelivr.net/gh/Dreamy-TZK/iemotion-pic@latest/img/猥琐萌/12.jpg"},{"name":"120","url":"https://cdn.jsdelivr.net/gh/Dreamy-TZK/iemotion-pic@latest/img/猥琐萌/120.jpg"},{"name":"121","url":"https://cdn.jsdelivr.net/gh/Dreamy-TZK/iemotion-pic@latest/img/猥琐萌/121.jpg"},{"name":"122","url":"https://cdn.jsdelivr.net/gh/Dreamy-TZK/iemotion-pic@latest/img/猥琐萌/122.jpg"},{"name":"123","url":"https://cdn.jsdelivr.net/gh/Dreamy-TZK/iemotion-pic@latest/img/猥琐萌/123.jpg"},{"name":"124","url":"https://cdn.jsdelivr.net/gh/Dreamy-TZK/iemotion-pic@latest/img/猥琐萌/124.jpg"},{"name":"125","url":"https://cdn.jsdelivr.net/gh/Dreamy-TZK/iemotion-pic@latest/img/猥琐萌/125.jpg"},{"name":"126","url":"https://cdn.jsdelivr.net/gh/Dreamy-TZK/iemotion-pic@latest/img/猥琐萌/126.jpg"},{"name":"127","url":"https://cdn.jsdelivr.net/gh/Dreamy-TZK/iemotion-pic@latest/img/猥琐萌/127.jpg"},{"name":"128","url":"https://cdn.jsdelivr.net/gh/Dreamy-TZK/iemotion-pic@latest/img/猥琐萌/128.jpg"},{"name":"129","url":"https://cdn.jsdelivr.net/gh/Dreamy-TZK/iemotion-pic@latest/img/猥琐萌/129.jpg"},{"name":"13","url":"https://cdn.jsdelivr.net/gh/Dreamy-TZK/iemotion-pic@latest/img/猥琐萌/13.jpg"},{"name":"130","url":"https://cdn.jsdelivr.net/gh/Dreamy-TZK/iemotion-pic@latest/img/猥琐萌/130.jpg"},{"name":"131","url":"https://cdn.jsdelivr.net/gh/Dreamy-TZK/iemotion-pic@latest/img/猥琐萌/131.jpg"},{"name":"132","url":"https://cdn.jsdelivr.net/gh/Dreamy-TZK/iemotion-pic@latest/img/猥琐萌/132.jpg"},{"name":"133","url":"https://cdn.jsdelivr.net/gh/Dreamy-TZK/iemotion-pic@latest/img/猥琐萌/133.jpg"},{"name":"134","url":"https://cdn.jsdelivr.net/gh/Dreamy-TZK/iemotion-pic@latest/img/猥琐萌/134.jpg"},{"name":"135","url":"https://cdn.jsdelivr.net/gh/Dreamy-TZK/iemotion-pic@latest/img/猥琐萌/135.jpg"},{"name":"136","url":"https://cdn.jsdelivr.net/gh/Dreamy-TZK/iemotion-pic@latest/img/猥琐萌/136.jpg"},{"name":"137","url":"https://cdn.jsdelivr.net/gh/Dreamy-TZK/iemotion-pic@latest/img/猥琐萌/137.jpg"},{"name":"138","url":"https://cdn.jsdelivr.net/gh/Dreamy-TZK/iemotion-pic@latest/img/猥琐萌/138.jpg"},{"name":"139","url":"https://cdn.jsdelivr.net/gh/Dreamy-TZK/iemotion-pic@latest/img/猥琐萌/139.jpg"},{"name":"14","url":"https://cdn.jsdelivr.net/gh/Dreamy-TZK/iemotion-pic@latest/img/猥琐萌/14.jpg"},{"name":"140","url":"https://cdn.jsdelivr.net/gh/Dreamy-TZK/iemotion-pic@latest/img/猥琐萌/140.jpg"},{"name":"141","url":"https://cdn.jsdelivr.net/gh/Dreamy-TZK/iemotion-pic@latest/img/猥琐萌/141.jpg"},{"name":"142","url":"https://cdn.jsdelivr.net/gh/Dreamy-TZK/iemotion-pic@latest/img/猥琐萌/142.jpg"},{"name":"143","url":"https://cdn.jsdelivr.net/gh/Dreamy-TZK/iemotion-pic@latest/img/猥琐萌/143.jpg"},{"name":"144","url":"https://cdn.jsdelivr.net/gh/Dreamy-TZK/iemotion-pic@latest/img/猥琐萌/144.jpg"},{"name":"145","url":"https://cdn.jsdelivr.net/gh/Dreamy-TZK/iemotion-pic@latest/img/猥琐萌/145.jpg"},{"name":"146","url":"https://cdn.jsdelivr.net/gh/Dreamy-TZK/iemotion-pic@latest/img/猥琐萌/146.jpg"},{"name":"147","url":"https://cdn.jsdelivr.net/gh/Dreamy-TZK/iemotion-pic@latest/img/猥琐萌/147.jpg"},{"name":"148","url":"https://cdn.jsdelivr.net/gh/Dreamy-TZK/iemotion-pic@latest/img/猥琐萌/148.jpg"},{"name":"149","url":"https://cdn.jsdelivr.net/gh/Dreamy-TZK/iemotion-pic@latest/img/猥琐萌/149.jpg"},{"name":"15","url":"https://cdn.jsdelivr.net/gh/Dreamy-TZK/iemotion-pic@latest/img/猥琐萌/15.jpg"},{"name":"150","url":"https://cdn.jsdelivr.net/gh/Dreamy-TZK/iemotion-pic@latest/img/猥琐萌/150.jpg"},{"name":"151","url":"https://cdn.jsdelivr.net/gh/Dreamy-TZK/iemotion-pic@latest/img/猥琐萌/151.jpg"},{"name":"152","url":"https://cdn.jsdelivr.net/gh/Dreamy-TZK/iemotion-pic@latest/img/猥琐萌/152.jpg"},{"name":"153","url":"https://cdn.jsdelivr.net/gh/Dreamy-TZK/iemotion-pic@latest/img/猥琐萌/153.jpg"},{"name":"154","url":"https://cdn.jsdelivr.net/gh/Dreamy-TZK/iemotion-pic@latest/img/猥琐萌/154.jpg"},{"name":"155","url":"https://cdn.jsdelivr.net/gh/Dreamy-TZK/iemotion-pic@latest/img/猥琐萌/155.jpg"},{"name":"156","url":"https://cdn.jsdelivr.net/gh/Dreamy-TZK/iemotion-pic@latest/img/猥琐萌/156.jpg"},{"name":"157","url":"https://cdn.jsdelivr.net/gh/Dreamy-TZK/iemotion-pic@latest/img/猥琐萌/157.jpg"},{"name":"158","url":"https://cdn.jsdelivr.net/gh/Dreamy-TZK/iemotion-pic@latest/img/猥琐萌/158.jpg"},{"name":"159","url":"https://cdn.jsdelivr.net/gh/Dreamy-TZK/iemotion-pic@latest/img/猥琐萌/159.jpg"},{"name":"16","url":"https://cdn.jsdelivr.net/gh/Dreamy-TZK/iemotion-pic@latest/img/猥琐萌/16.jpg"},{"name":"160","url":"https://cdn.jsdelivr.net/gh/Dreamy-TZK/iemotion-pic@latest/img/猥琐萌/160.jpg"},{"name":"161","url":"https://cdn.jsdelivr.net/gh/Dreamy-TZK/iemotion-pic@latest/img/猥琐萌/161.jpg"},{"name":"162","url":"https://cdn.jsdelivr.net/gh/Dreamy-TZK/iemotion-pic@latest/img/猥琐萌/162.jpg"},{"name":"163","url":"https://cdn.jsdelivr.net/gh/Dreamy-TZK/iemotion-pic@latest/img/猥琐萌/163.jpg"},{"name":"164","url":"https://cdn.jsdelivr.net/gh/Dreamy-TZK/iemotion-pic@latest/img/猥琐萌/164.jpg"},{"name":"165","url":"https://cdn.jsdelivr.net/gh/Dreamy-TZK/iemotion-pic@latest/img/猥琐萌/165.jpg"},{"name":"166","url":"https://cdn.jsdelivr.net/gh/Dreamy-TZK/iemotion-pic@latest/img/猥琐萌/166.jpg"},{"name":"167","url":"https://cdn.jsdelivr.net/gh/Dreamy-TZK/iemotion-pic@latest/img/猥琐萌/167.jpg"},{"name":"168","url":"https://cdn.jsdelivr.net/gh/Dreamy-TZK/iemotion-pic@latest/img/猥琐萌/168.jpg"},{"name":"169","url":"https://cdn.jsdelivr.net/gh/Dreamy-TZK/iemotion-pic@latest/img/猥琐萌/169.jpg"},{"name":"17","url":"https://cdn.jsdelivr.net/gh/Dreamy-TZK/iemotion-pic@latest/img/猥琐萌/17.jpg"},{"name":"170","url":"https://cdn.jsdelivr.net/gh/Dreamy-TZK/iemotion-pic@latest/img/猥琐萌/170.jpg"},{"name":"171","url":"https://cdn.jsdelivr.net/gh/Dreamy-TZK/iemotion-pic@latest/img/猥琐萌/171.jpg"},{"name":"172","url":"https://cdn.jsdelivr.net/gh/Dreamy-TZK/iemotion-pic@latest/img/猥琐萌/172.jpg"},{"name":"173","url":"https://cdn.jsdelivr.net/gh/Dreamy-TZK/iemotion-pic@latest/img/猥琐萌/173.jpg"},{"name":"174","url":"https://cdn.jsdelivr.net/gh/Dreamy-TZK/iemotion-pic@latest/img/猥琐萌/174.jpg"},{"name":"175","url":"https://cdn.jsdelivr.net/gh/Dreamy-TZK/iemotion-pic@latest/img/猥琐萌/175.jpg"},{"name":"176","url":"https://cdn.jsdelivr.net/gh/Dreamy-TZK/iemotion-pic@latest/img/猥琐萌/176.jpg"},{"name":"177","url":"https://cdn.jsdelivr.net/gh/Dreamy-TZK/iemotion-pic@latest/img/猥琐萌/177.jpg"},{"name":"178","url":"https://cdn.jsdelivr.net/gh/Dreamy-TZK/iemotion-pic@latest/img/猥琐萌/178.jpg"},{"name":"179","url":"https://cdn.jsdelivr.net/gh/Dreamy-TZK/iemotion-pic@latest/img/猥琐萌/179.jpg"},{"name":"18","url":"https://cdn.jsdelivr.net/gh/Dreamy-TZK/iemotion-pic@latest/img/猥琐萌/18.jpg"},{"name":"180","url":"https://cdn.jsdelivr.net/gh/Dreamy-TZK/iemotion-pic@latest/img/猥琐萌/180.jpg"},{"name":"181","url":"https://cdn.jsdelivr.net/gh/Dreamy-TZK/iemotion-pic@latest/img/猥琐萌/181.jpg"},{"name":"182","url":"https://cdn.jsdelivr.net/gh/Dreamy-TZK/iemotion-pic@latest/img/猥琐萌/182.jpg"},{"name":"183","url":"https://cdn.jsdelivr.net/gh/Dreamy-TZK/iemotion-pic@latest/img/猥琐萌/183.jpg"},{"name":"184","url":"https://cdn.jsdelivr.net/gh/Dreamy-TZK/iemotion-pic@latest/img/猥琐萌/184.jpg"},{"name":"185","url":"https://cdn.jsdelivr.net/gh/Dreamy-TZK/iemotion-pic@latest/img/猥琐萌/185.jpg"},{"name":"186","url":"https://cdn.jsdelivr.net/gh/Dreamy-TZK/iemotion-pic@latest/img/猥琐萌/186.jpg"},{"name":"187","url":"https://cdn.jsdelivr.net/gh/Dreamy-TZK/iemotion-pic@latest/img/猥琐萌/187.jpg"},{"name":"188","url":"https://cdn.jsdelivr.net/gh/Dreamy-TZK/iemotion-pic@latest/img/猥琐萌/188.jpg"},{"name":"189","url":"https://cdn.jsdelivr.net/gh/Dreamy-TZK/iemotion-pic@latest/img/猥琐萌/189.jpg"},{"name":"19","url":"https://cdn.jsdelivr.net/gh/Dreamy-TZK/iemotion-pic@latest/img/猥琐萌/19.jpg"},{"name":"190","url":"https://cdn.jsdelivr.net/gh/Dreamy-TZK/iemotion-pic@latest/img/猥琐萌/190.jpg"},{"name":"191","url":"https://cdn.jsdelivr.net/gh/Dreamy-TZK/iemotion-pic@latest/img/猥琐萌/191.jpg"},{"name":"192","url":"https://cdn.jsdelivr.net/gh/Dreamy-TZK/iemotion-pic@latest/img/猥琐萌/192.jpg"},{"name":"193","url":"https://cdn.jsdelivr.net/gh/Dreamy-TZK/iemotion-pic@latest/img/猥琐萌/193.jpg"},{"name":"194","url":"https://cdn.jsdelivr.net/gh/Dreamy-TZK/iemotion-pic@latest/img/猥琐萌/194.jpg"},{"name":"195","url":"https://cdn.jsdelivr.net/gh/Dreamy-TZK/iemotion-pic@latest/img/猥琐萌/195.jpg"},{"name":"196","url":"https://cdn.jsdelivr.net/gh/Dreamy-TZK/iemotion-pic@latest/img/猥琐萌/196.jpg"},{"name":"197","url":"https://cdn.jsdelivr.net/gh/Dreamy-TZK/iemotion-pic@latest/img/猥琐萌/197.jpg"},{"name":"198","url":"https://cdn.jsdelivr.net/gh/Dreamy-TZK/iemotion-pic@latest/img/猥琐萌/198.jpg"},{"name":"199","url":"https://cdn.jsdelivr.net/gh/Dreamy-TZK/iemotion-pic@latest/img/猥琐萌/199.jpg"},{"name":"2","url":"https://cdn.jsdelivr.net/gh/Dreamy-TZK/iemotion-pic@latest/img/猥琐萌/2.jpg"},{"name":"20","url":"https://cdn.jsdelivr.net/gh/Dreamy-TZK/iemotion-pic@latest/img/猥琐萌/20.jpg"},{"name":"200","url":"https://cdn.jsdelivr.net/gh/Dreamy-TZK/iemotion-pic@latest/img/猥琐萌/200.jpg"},{"name":"201","url":"https://cdn.jsdelivr.net/gh/Dreamy-TZK/iemotion-pic@latest/img/猥琐萌/201.jpg"},{"name":"202","url":"https://cdn.jsdelivr.net/gh/Dreamy-TZK/iemotion-pic@latest/img/猥琐萌/202.jpg"},{"name":"203","url":"https://cdn.jsdelivr.net/gh/Dreamy-TZK/iemotion-pic@latest/img/猥琐萌/203.jpg"},{"name":"204","url":"https://cdn.jsdelivr.net/gh/Dreamy-TZK/iemotion-pic@latest/img/猥琐萌/204.jpg"},{"name":"205","url":"https://cdn.jsdelivr.net/gh/Dreamy-TZK/iemotion-pic@latest/img/猥琐萌/205.jpg"},{"name":"206","url":"https://cdn.jsdelivr.net/gh/Dreamy-TZK/iemotion-pic@latest/img/猥琐萌/206.jpg"},{"name":"207","url":"https://cdn.jsdelivr.net/gh/Dreamy-TZK/iemotion-pic@latest/img/猥琐萌/207.jpg"},{"name":"208","url":"https://cdn.jsdelivr.net/gh/Dreamy-TZK/iemotion-pic@latest/img/猥琐萌/208.jpg"},{"name":"209","url":"https://cdn.jsdelivr.net/gh/Dreamy-TZK/iemotion-pic@latest/img/猥琐萌/209.jpg"},{"name":"21","url":"https://cdn.jsdelivr.net/gh/Dreamy-TZK/iemotion-pic@latest/img/猥琐萌/21.jpg"},{"name":"210","url":"https://cdn.jsdelivr.net/gh/Dreamy-TZK/iemotion-pic@latest/img/猥琐萌/210.jpg"},{"name":"211","url":"https://cdn.jsdelivr.net/gh/Dreamy-TZK/iemotion-pic@latest/img/猥琐萌/211.jpg"},{"name":"212","url":"https://cdn.jsdelivr.net/gh/Dreamy-TZK/iemotion-pic@latest/img/猥琐萌/212.jpg"},{"name":"213","url":"https://cdn.jsdelivr.net/gh/Dreamy-TZK/iemotion-pic@latest/img/猥琐萌/213.jpg"},{"name":"214","url":"https://cdn.jsdelivr.net/gh/Dreamy-TZK/iemotion-pic@latest/img/猥琐萌/214.jpg"},{"name":"215","url":"https://cdn.jsdelivr.net/gh/Dreamy-TZK/iemotion-pic@latest/img/猥琐萌/215.jpg"},{"name":"216","url":"https://cdn.jsdelivr.net/gh/Dreamy-TZK/iemotion-pic@latest/img/猥琐萌/216.jpg"},{"name":"217","url":"https://cdn.jsdelivr.net/gh/Dreamy-TZK/iemotion-pic@latest/img/猥琐萌/217.jpg"},{"name":"218","url":"https://cdn.jsdelivr.net/gh/Dreamy-TZK/iemotion-pic@latest/img/猥琐萌/218.jpg"},{"name":"219","url":"https://cdn.jsdelivr.net/gh/Dreamy-TZK/iemotion-pic@latest/img/猥琐萌/219.jpg"},{"name":"22","url":"https://cdn.jsdelivr.net/gh/Dreamy-TZK/iemotion-pic@latest/img/猥琐萌/22.jpg"},{"name":"220","url":"https://cdn.jsdelivr.net/gh/Dreamy-TZK/iemotion-pic@latest/img/猥琐萌/220.jpg"},{"name":"221","url":"https://cdn.jsdelivr.net/gh/Dreamy-TZK/iemotion-pic@latest/img/猥琐萌/221.jpg"},{"name":"222","url":"https://cdn.jsdelivr.net/gh/Dreamy-TZK/iemotion-pic@latest/img/猥琐萌/222.jpg"},{"name":"223","url":"https://cdn.jsdelivr.net/gh/Dreamy-TZK/iemotion-pic@latest/img/猥琐萌/223.jpg"},{"name":"224","url":"https://cdn.jsdelivr.net/gh/Dreamy-TZK/iemotion-pic@latest/img/猥琐萌/224.jpg"},{"name":"225","url":"https://cdn.jsdelivr.net/gh/Dreamy-TZK/iemotion-pic@latest/img/猥琐萌/225.jpg"},{"name":"226","url":"https://cdn.jsdelivr.net/gh/Dreamy-TZK/iemotion-pic@latest/img/猥琐萌/226.jpg"},{"name":"227","url":"https://cdn.jsdelivr.net/gh/Dreamy-TZK/iemotion-pic@latest/img/猥琐萌/227.jpg"},{"name":"228","url":"https://cdn.jsdelivr.net/gh/Dreamy-TZK/iemotion-pic@latest/img/猥琐萌/228.jpg"},{"name":"229","url":"https://cdn.jsdelivr.net/gh/Dreamy-TZK/iemotion-pic@latest/img/猥琐萌/229.jpg"},{"name":"23","url":"https://cdn.jsdelivr.net/gh/Dreamy-TZK/iemotion-pic@latest/img/猥琐萌/23.jpg"},{"name":"230","url":"https://cdn.jsdelivr.net/gh/Dreamy-TZK/iemotion-pic@latest/img/猥琐萌/230.jpg"},{"name":"231","url":"https://cdn.jsdelivr.net/gh/Dreamy-TZK/iemotion-pic@latest/img/猥琐萌/231.jpg"},{"name":"232","url":"https://cdn.jsdelivr.net/gh/Dreamy-TZK/iemotion-pic@latest/img/猥琐萌/232.jpg"},{"name":"233","url":"https://cdn.jsdelivr.net/gh/Dreamy-TZK/iemotion-pic@latest/img/猥琐萌/233.jpg"},{"name":"234","url":"https://cdn.jsdelivr.net/gh/Dreamy-TZK/iemotion-pic@latest/img/猥琐萌/234.jpg"},{"name":"235","url":"https://cdn.jsdelivr.net/gh/Dreamy-TZK/iemotion-pic@latest/img/猥琐萌/235.jpg"},{"name":"236","url":"https://cdn.jsdelivr.net/gh/Dreamy-TZK/iemotion-pic@latest/img/猥琐萌/236.jpg"},{"name":"237","url":"https://cdn.jsdelivr.net/gh/Dreamy-TZK/iemotion-pic@latest/img/猥琐萌/237.jpg"},{"name":"238","url":"https://cdn.jsdelivr.net/gh/Dreamy-TZK/iemotion-pic@latest/img/猥琐萌/238.jpg"},{"name":"239","url":"https://cdn.jsdelivr.net/gh/Dreamy-TZK/iemotion-pic@latest/img/猥琐萌/239.jpg"},{"name":"24","url":"https://cdn.jsdelivr.net/gh/Dreamy-TZK/iemotion-pic@latest/img/猥琐萌/24.jpg"},{"name":"240","url":"https://cdn.jsdelivr.net/gh/Dreamy-TZK/iemotion-pic@latest/img/猥琐萌/240.jpg"},{"name":"241","url":"https://cdn.jsdelivr.net/gh/Dreamy-TZK/iemotion-pic@latest/img/猥琐萌/241.jpg"},{"name":"242","url":"https://cdn.jsdelivr.net/gh/Dreamy-TZK/iemotion-pic@latest/img/猥琐萌/242.jpg"},{"name":"243","url":"https://cdn.jsdelivr.net/gh/Dreamy-TZK/iemotion-pic@latest/img/猥琐萌/243.jpg"},{"name":"244","url":"https://cdn.jsdelivr.net/gh/Dreamy-TZK/iemotion-pic@latest/img/猥琐萌/244.jpg"},{"name":"245","url":"https://cdn.jsdelivr.net/gh/Dreamy-TZK/iemotion-pic@latest/img/猥琐萌/245.jpg"},{"name":"246","url":"https://cdn.jsdelivr.net/gh/Dreamy-TZK/iemotion-pic@latest/img/猥琐萌/246.jpg"},{"name":"247","url":"https://cdn.jsdelivr.net/gh/Dreamy-TZK/iemotion-pic@latest/img/猥琐萌/247.jpeg"},{"name":"248","url":"https://cdn.jsdelivr.net/gh/Dreamy-TZK/iemotion-pic@latest/img/猥琐萌/248.jpg"},{"name":"249","url":"https://cdn.jsdelivr.net/gh/Dreamy-TZK/iemotion-pic@latest/img/猥琐萌/249.jpg"},{"name":"25","url":"https://cdn.jsdelivr.net/gh/Dreamy-TZK/iemotion-pic@latest/img/猥琐萌/25.jpg"},{"name":"250","url":"https://cdn.jsdelivr.net/gh/Dreamy-TZK/iemotion-pic@latest/img/猥琐萌/250.jpg"},{"name":"251","url":"https://cdn.jsdelivr.net/gh/Dreamy-TZK/iemotion-pic@latest/img/猥琐萌/251.jpg"},{"name":"252","url":"https://cdn.jsdelivr.net/gh/Dreamy-TZK/iemotion-pic@latest/img/猥琐萌/252.jpg"},{"name":"253","url":"https://cdn.jsdelivr.net/gh/Dreamy-TZK/iemotion-pic@latest/img/猥琐萌/253.jpg"},{"name":"254","url":"https://cdn.jsdelivr.net/gh/Dreamy-TZK/iemotion-pic@latest/img/猥琐萌/254.jpg"},{"name":"255","url":"https://cdn.jsdelivr.net/gh/Dreamy-TZK/iemotion-pic@latest/img/猥琐萌/255.jpg"},{"name":"256","url":"https://cdn.jsdelivr.net/gh/Dreamy-TZK/iemotion-pic@latest/img/猥琐萌/256.jpg"},{"name":"257","url":"https://cdn.jsdelivr.net/gh/Dreamy-TZK/iemotion-pic@latest/img/猥琐萌/257.jpg"},{"name":"258","url":"https://cdn.jsdelivr.net/gh/Dreamy-TZK/iemotion-pic@latest/img/猥琐萌/258.jpg"},{"name":"259","url":"https://cdn.jsdelivr.net/gh/Dreamy-TZK/iemotion-pic@latest/img/猥琐萌/259.jpg"},{"name":"26","url":"https://cdn.jsdelivr.net/gh/Dreamy-TZK/iemotion-pic@latest/img/猥琐萌/26.jpg"},{"name":"260","url":"https://cdn.jsdelivr.net/gh/Dreamy-TZK/iemotion-pic@latest/img/猥琐萌/260.jpg"},{"name":"261","url":"https://cdn.jsdelivr.net/gh/Dreamy-TZK/iemotion-pic@latest/img/猥琐萌/261.jpg"},{"name":"262","url":"https://cdn.jsdelivr.net/gh/Dreamy-TZK/iemotion-pic@latest/img/猥琐萌/262.jpg"},{"name":"263","url":"https://cdn.jsdelivr.net/gh/Dreamy-TZK/iemotion-pic@latest/img/猥琐萌/263.jpg"},{"name":"264","url":"https://cdn.jsdelivr.net/gh/Dreamy-TZK/iemotion-pic@latest/img/猥琐萌/264.jpg"},{"name":"265","url":"https://cdn.jsdelivr.net/gh/Dreamy-TZK/iemotion-pic@latest/img/猥琐萌/265.jpg"},{"name":"266","url":"https://cdn.jsdelivr.net/gh/Dreamy-TZK/iemotion-pic@latest/img/猥琐萌/266.jpg"},{"name":"267","url":"https://cdn.jsdelivr.net/gh/Dreamy-TZK/iemotion-pic@latest/img/猥琐萌/267.jpg"},{"name":"268","url":"https://cdn.jsdelivr.net/gh/Dreamy-TZK/iemotion-pic@latest/img/猥琐萌/268.jpg"},{"name":"269","url":"https://cdn.jsdelivr.net/gh/Dreamy-TZK/iemotion-pic@latest/img/猥琐萌/269.jpg"},{"name":"27","url":"https://cdn.jsdelivr.net/gh/Dreamy-TZK/iemotion-pic@latest/img/猥琐萌/27.jpg"},{"name":"270","url":"https://cdn.jsdelivr.net/gh/Dreamy-TZK/iemotion-pic@latest/img/猥琐萌/270.jpg"},{"name":"271","url":"https://cdn.jsdelivr.net/gh/Dreamy-TZK/iemotion-pic@latest/img/猥琐萌/271.jpg"},{"name":"272","url":"https://cdn.jsdelivr.net/gh/Dreamy-TZK/iemotion-pic@latest/img/猥琐萌/272.jpg"},{"name":"273","url":"https://cdn.jsdelivr.net/gh/Dreamy-TZK/iemotion-pic@latest/img/猥琐萌/273.jpg"},{"name":"274","url":"https://cdn.jsdelivr.net/gh/Dreamy-TZK/iemotion-pic@latest/img/猥琐萌/274.jpg"},{"name":"275","url":"https://cdn.jsdelivr.net/gh/Dreamy-TZK/iemotion-pic@latest/img/猥琐萌/275.jpg"},{"name":"276","url":"https://cdn.jsdelivr.net/gh/Dreamy-TZK/iemotion-pic@latest/img/猥琐萌/276.jpg"},{"name":"277","url":"https://cdn.jsdelivr.net/gh/Dreamy-TZK/iemotion-pic@latest/img/猥琐萌/277.jpg"},{"name":"278","url":"https://cdn.jsdelivr.net/gh/Dreamy-TZK/iemotion-pic@latest/img/猥琐萌/278.jpg"},{"name":"279","url":"https://cdn.jsdelivr.net/gh/Dreamy-TZK/iemotion-pic@latest/img/猥琐萌/279.jpg"},{"name":"28","url":"https://cdn.jsdelivr.net/gh/Dreamy-TZK/iemotion-pic@latest/img/猥琐萌/28.jpg"},{"name":"280","url":"https://cdn.jsdelivr.net/gh/Dreamy-TZK/iemotion-pic@latest/img/猥琐萌/280.jpg"},{"name":"281","url":"https://cdn.jsdelivr.net/gh/Dreamy-TZK/iemotion-pic@latest/img/猥琐萌/281.jpg"},{"name":"282","url":"https://cdn.jsdelivr.net/gh/Dreamy-TZK/iemotion-pic@latest/img/猥琐萌/282.jpg"},{"name":"283","url":"https://cdn.jsdelivr.net/gh/Dreamy-TZK/iemotion-pic@latest/img/猥琐萌/283.jpg"},{"name":"284","url":"https://cdn.jsdelivr.net/gh/Dreamy-TZK/iemotion-pic@latest/img/猥琐萌/284.jpg"},{"name":"285","url":"https://cdn.jsdelivr.net/gh/Dreamy-TZK/iemotion-pic@latest/img/猥琐萌/285.jpg"},{"name":"286","url":"https://cdn.jsdelivr.net/gh/Dreamy-TZK/iemotion-pic@latest/img/猥琐萌/286.jpg"},{"name":"287","url":"https://cdn.jsdelivr.net/gh/Dreamy-TZK/iemotion-pic@latest/img/猥琐萌/287.gif"},{"name":"288","url":"https://cdn.jsdelivr.net/gh/Dreamy-TZK/iemotion-pic@latest/img/猥琐萌/288.jpg"},{"name":"289","url":"https://cdn.jsdelivr.net/gh/Dreamy-TZK/iemotion-pic@latest/img/猥琐萌/289.jpg"},{"name":"29","url":"https://cdn.jsdelivr.net/gh/Dreamy-TZK/iemotion-pic@latest/img/猥琐萌/29.jpg"},{"name":"290","url":"https://cdn.jsdelivr.net/gh/Dreamy-TZK/iemotion-pic@latest/img/猥琐萌/290.jpg"},{"name":"291","url":"https://cdn.jsdelivr.net/gh/Dreamy-TZK/iemotion-pic@latest/img/猥琐萌/291.jpg"},{"name":"292","url":"https://cdn.jsdelivr.net/gh/Dreamy-TZK/iemotion-pic@latest/img/猥琐萌/292.jpg"},{"name":"293","url":"https://cdn.jsdelivr.net/gh/Dreamy-TZK/iemotion-pic@latest/img/猥琐萌/293.jpg"},{"name":"294","url":"https://cdn.jsdelivr.net/gh/Dreamy-TZK/iemotion-pic@latest/img/猥琐萌/294.jpg"},{"name":"295","url":"https://cdn.jsdelivr.net/gh/Dreamy-TZK/iemotion-pic@latest/img/猥琐萌/295.jpg"},{"name":"296","url":"https://cdn.jsdelivr.net/gh/Dreamy-TZK/iemotion-pic@latest/img/猥琐萌/296.gif"},{"name":"297","url":"https://cdn.jsdelivr.net/gh/Dreamy-TZK/iemotion-pic@latest/img/猥琐萌/297.jpg"},{"name":"298","url":"https://cdn.jsdelivr.net/gh/Dreamy-TZK/iemotion-pic@latest/img/猥琐萌/298.gif"},{"name":"299","url":"https://cdn.jsdelivr.net/gh/Dreamy-TZK/iemotion-pic@latest/img/猥琐萌/299.jpg"},{"name":"3","url":"https://cdn.jsdelivr.net/gh/Dreamy-TZK/iemotion-pic@latest/img/猥琐萌/3.jpg"},{"name":"30","url":"https://cdn.jsdelivr.net/gh/Dreamy-TZK/iemotion-pic@latest/img/猥琐萌/30.jpg"},{"name":"300","url":"https://cdn.jsdelivr.net/gh/Dreamy-TZK/iemotion-pic@latest/img/猥琐萌/300.jpg"},{"name":"301","url":"https://cdn.jsdelivr.net/gh/Dreamy-TZK/iemotion-pic@latest/img/猥琐萌/301.jpg"},{"name":"302","url":"https://cdn.jsdelivr.net/gh/Dreamy-TZK/iemotion-pic@latest/img/猥琐萌/302.jpg"},{"name":"303","url":"https://cdn.jsdelivr.net/gh/Dreamy-TZK/iemotion-pic@latest/img/猥琐萌/303.jpg"},{"name":"304","url":"https://cdn.jsdelivr.net/gh/Dreamy-TZK/iemotion-pic@latest/img/猥琐萌/304.jpg"},{"name":"305","url":"https://cdn.jsdelivr.net/gh/Dreamy-TZK/iemotion-pic@latest/img/猥琐萌/305.jpg"},{"name":"306","url":"https://cdn.jsdelivr.net/gh/Dreamy-TZK/iemotion-pic@latest/img/猥琐萌/306.jpg"},{"name":"307","url":"https://cdn.jsdelivr.net/gh/Dreamy-TZK/iemotion-pic@latest/img/猥琐萌/307.jpg"},{"name":"308","url":"https://cdn.jsdelivr.net/gh/Dreamy-TZK/iemotion-pic@latest/img/猥琐萌/308.jpg"},{"name":"309","url":"https://cdn.jsdelivr.net/gh/Dreamy-TZK/iemotion-pic@latest/img/猥琐萌/309.jpg"},{"name":"31","url":"https://cdn.jsdelivr.net/gh/Dreamy-TZK/iemotion-pic@latest/img/猥琐萌/31.jpg"},{"name":"310","url":"https://cdn.jsdelivr.net/gh/Dreamy-TZK/iemotion-pic@latest/img/猥琐萌/310.gif"},{"name":"311","url":"https://cdn.jsdelivr.net/gh/Dreamy-TZK/iemotion-pic@latest/img/猥琐萌/311.jpg"},{"name":"312","url":"https://cdn.jsdelivr.net/gh/Dreamy-TZK/iemotion-pic@latest/img/猥琐萌/312.gif"},{"name":"313","url":"https://cdn.jsdelivr.net/gh/Dreamy-TZK/iemotion-pic@latest/img/猥琐萌/313.jpg"},{"name":"314","url":"https://cdn.jsdelivr.net/gh/Dreamy-TZK/iemotion-pic@latest/img/猥琐萌/314.jpg"},{"name":"315","url":"https://cdn.jsdelivr.net/gh/Dreamy-TZK/iemotion-pic@latest/img/猥琐萌/315.jpg"},{"name":"316","url":"https://cdn.jsdelivr.net/gh/Dreamy-TZK/iemotion-pic@latest/img/猥琐萌/316.jpg"},{"name":"317","url":"https://cdn.jsdelivr.net/gh/Dreamy-TZK/iemotion-pic@latest/img/猥琐萌/317.jpg"},{"name":"318","url":"https://cdn.jsdelivr.net/gh/Dreamy-TZK/iemotion-pic@latest/img/猥琐萌/318.jpg"},{"name":"319","url":"https://cdn.jsdelivr.net/gh/Dreamy-TZK/iemotion-pic@latest/img/猥琐萌/319.jpg"},{"name":"32","url":"https://cdn.jsdelivr.net/gh/Dreamy-TZK/iemotion-pic@latest/img/猥琐萌/32.jpg"},{"name":"320","url":"https://cdn.jsdelivr.net/gh/Dreamy-TZK/iemotion-pic@latest/img/猥琐萌/320.jpg"},{"name":"321","url":"https://cdn.jsdelivr.net/gh/Dreamy-TZK/iemotion-pic@latest/img/猥琐萌/321.jpg"},{"name":"322","url":"https://cdn.jsdelivr.net/gh/Dreamy-TZK/iemotion-pic@latest/img/猥琐萌/322.jpg"},{"name":"323","url":"https://cdn.jsdelivr.net/gh/Dreamy-TZK/iemotion-pic@latest/img/猥琐萌/323.jpg"},{"name":"324","url":"https://cdn.jsdelivr.net/gh/Dreamy-TZK/iemotion-pic@latest/img/猥琐萌/324.jpg"},{"name":"325","url":"https://cdn.jsdelivr.net/gh/Dreamy-TZK/iemotion-pic@latest/img/猥琐萌/325.jpg"},{"name":"326","url":"https://cdn.jsdelivr.net/gh/Dreamy-TZK/iemotion-pic@latest/img/猥琐萌/326.gif"},{"name":"327","url":"https://cdn.jsdelivr.net/gh/Dreamy-TZK/iemotion-pic@latest/img/猥琐萌/327.jpg"},{"name":"33","url":"https://cdn.jsdelivr.net/gh/Dreamy-TZK/iemotion-pic@latest/img/猥琐萌/33.jpg"},{"name":"34","url":"https://cdn.jsdelivr.net/gh/Dreamy-TZK/iemotion-pic@latest/img/猥琐萌/34.jpg"},{"name":"35","url":"https://cdn.jsdelivr.net/gh/Dreamy-TZK/iemotion-pic@latest/img/猥琐萌/35.jpg"},{"name":"36","url":"https://cdn.jsdelivr.net/gh/Dreamy-TZK/iemotion-pic@latest/img/猥琐萌/36.jpg"},{"name":"37","url":"https://cdn.jsdelivr.net/gh/Dreamy-TZK/iemotion-pic@latest/img/猥琐萌/37.jpg"},{"name":"38","url":"https://cdn.jsdelivr.net/gh/Dreamy-TZK/iemotion-pic@latest/img/猥琐萌/38.jpg"},{"name":"39","url":"https://cdn.jsdelivr.net/gh/Dreamy-TZK/iemotion-pic@latest/img/猥琐萌/39.jpg"},{"name":"4","url":"https://cdn.jsdelivr.net/gh/Dreamy-TZK/iemotion-pic@latest/img/猥琐萌/4.jpg"},{"name":"40","url":"https://cdn.jsdelivr.net/gh/Dreamy-TZK/iemotion-pic@latest/img/猥琐萌/40.jpg"},{"name":"41","url":"https://cdn.jsdelivr.net/gh/Dreamy-TZK/iemotion-pic@latest/img/猥琐萌/41.jpg"},{"name":"42","url":"https://cdn.jsdelivr.net/gh/Dreamy-TZK/iemotion-pic@latest/img/猥琐萌/42.jpg"},{"name":"43","url":"https://cdn.jsdelivr.net/gh/Dreamy-TZK/iemotion-pic@latest/img/猥琐萌/43.jpg"},{"name":"44","url":"https://cdn.jsdelivr.net/gh/Dreamy-TZK/iemotion-pic@latest/img/猥琐萌/44.jpg"},{"name":"45","url":"https://cdn.jsdelivr.net/gh/Dreamy-TZK/iemotion-pic@latest/img/猥琐萌/45.jpg"},{"name":"46","url":"https://cdn.jsdelivr.net/gh/Dreamy-TZK/iemotion-pic@latest/img/猥琐萌/46.jpg"},{"name":"47","url":"https://cdn.jsdelivr.net/gh/Dreamy-TZK/iemotion-pic@latest/img/猥琐萌/47.jpg"},{"name":"48","url":"https://cdn.jsdelivr.net/gh/Dreamy-TZK/iemotion-pic@latest/img/猥琐萌/48.jpg"},{"name":"49","url":"https://cdn.jsdelivr.net/gh/Dreamy-TZK/iemotion-pic@latest/img/猥琐萌/49.jpg"},{"name":"5","url":"https://cdn.jsdelivr.net/gh/Dreamy-TZK/iemotion-pic@latest/img/猥琐萌/5.jpg"},{"name":"50","url":"https://cdn.jsdelivr.net/gh/Dreamy-TZK/iemotion-pic@latest/img/猥琐萌/50.jpg"},{"name":"51","url":"https://cdn.jsdelivr.net/gh/Dreamy-TZK/iemotion-pic@latest/img/猥琐萌/51.jpg"},{"name":"52","url":"https://cdn.jsdelivr.net/gh/Dreamy-TZK/iemotion-pic@latest/img/猥琐萌/52.jpg"},{"name":"53","url":"https://cdn.jsdelivr.net/gh/Dreamy-TZK/iemotion-pic@latest/img/猥琐萌/53.jpg"},{"name":"54","url":"https://cdn.jsdelivr.net/gh/Dreamy-TZK/iemotion-pic@latest/img/猥琐萌/54.jpg"},{"name":"55","url":"https://cdn.jsdelivr.net/gh/Dreamy-TZK/iemotion-pic@latest/img/猥琐萌/55.jpg"},{"name":"56","url":"https://cdn.jsdelivr.net/gh/Dreamy-TZK/iemotion-pic@latest/img/猥琐萌/56.jpg"},{"name":"57","url":"https://cdn.jsdelivr.net/gh/Dreamy-TZK/iemotion-pic@latest/img/猥琐萌/57.jpg"},{"name":"58","url":"https://cdn.jsdelivr.net/gh/Dreamy-TZK/iemotion-pic@latest/img/猥琐萌/58.jpg"},{"name":"59","url":"https://cdn.jsdelivr.net/gh/Dreamy-TZK/iemotion-pic@latest/img/猥琐萌/59.jpg"},{"name":"6","url":"https://cdn.jsdelivr.net/gh/Dreamy-TZK/iemotion-pic@latest/img/猥琐萌/6.jpg"},{"name":"60","url":"https://cdn.jsdelivr.net/gh/Dreamy-TZK/iemotion-pic@latest/img/猥琐萌/60.jpg"},{"name":"61","url":"https://cdn.jsdelivr.net/gh/Dreamy-TZK/iemotion-pic@latest/img/猥琐萌/61.jpg"},{"name":"62","url":"https://cdn.jsdelivr.net/gh/Dreamy-TZK/iemotion-pic@latest/img/猥琐萌/62.jpg"},{"name":"63","url":"https://cdn.jsdelivr.net/gh/Dreamy-TZK/iemotion-pic@latest/img/猥琐萌/63.jpg"},{"name":"64","url":"https://cdn.jsdelivr.net/gh/Dreamy-TZK/iemotion-pic@latest/img/猥琐萌/64.jpg"},{"name":"65","url":"https://cdn.jsdelivr.net/gh/Dreamy-TZK/iemotion-pic@latest/img/猥琐萌/65.jpg"},{"name":"66","url":"https://cdn.jsdelivr.net/gh/Dreamy-TZK/iemotion-pic@latest/img/猥琐萌/66.jpg"},{"name":"67","url":"https://cdn.jsdelivr.net/gh/Dreamy-TZK/iemotion-pic@latest/img/猥琐萌/67.jpg"},{"name":"68","url":"https://cdn.jsdelivr.net/gh/Dreamy-TZK/iemotion-pic@latest/img/猥琐萌/68.jpg"},{"name":"69","url":"https://cdn.jsdelivr.net/gh/Dreamy-TZK/iemotion-pic@latest/img/猥琐萌/69.jpg"},{"name":"7","url":"https://cdn.jsdelivr.net/gh/Dreamy-TZK/iemotion-pic@latest/img/猥琐萌/7.jpg"},{"name":"70","url":"https://cdn.jsdelivr.net/gh/Dreamy-TZK/iemotion-pic@latest/img/猥琐萌/70.jpg"},{"name":"71","url":"https://cdn.jsdelivr.net/gh/Dreamy-TZK/iemotion-pic@latest/img/猥琐萌/71.jpg"},{"name":"72","url":"https://cdn.jsdelivr.net/gh/Dreamy-TZK/iemotion-pic@latest/img/猥琐萌/72.jpg"},{"name":"73","url":"https://cdn.jsdelivr.net/gh/Dreamy-TZK/iemotion-pic@latest/img/猥琐萌/73.jpg"},{"name":"74","url":"https://cdn.jsdelivr.net/gh/Dreamy-TZK/iemotion-pic@latest/img/猥琐萌/74.jpg"},{"name":"75","url":"https://cdn.jsdelivr.net/gh/Dreamy-TZK/iemotion-pic@latest/img/猥琐萌/75.jpg"},{"name":"76","url":"https://cdn.jsdelivr.net/gh/Dreamy-TZK/iemotion-pic@latest/img/猥琐萌/76.jpg"},{"name":"77","url":"https://cdn.jsdelivr.net/gh/Dreamy-TZK/iemotion-pic@latest/img/猥琐萌/77.jpg"},{"name":"78","url":"https://cdn.jsdelivr.net/gh/Dreamy-TZK/iemotion-pic@latest/img/猥琐萌/78.jpg"},{"name":"79","url":"https://cdn.jsdelivr.net/gh/Dreamy-TZK/iemotion-pic@latest/img/猥琐萌/79.jpg"},{"name":"8","url":"https://cdn.jsdelivr.net/gh/Dreamy-TZK/iemotion-pic@latest/img/猥琐萌/8.jpg"},{"name":"80","url":"https://cdn.jsdelivr.net/gh/Dreamy-TZK/iemotion-pic@latest/img/猥琐萌/80.jpg"},{"name":"81","url":"https://cdn.jsdelivr.net/gh/Dreamy-TZK/iemotion-pic@latest/img/猥琐萌/81.jpg"},{"name":"82","url":"https://cdn.jsdelivr.net/gh/Dreamy-TZK/iemotion-pic@latest/img/猥琐萌/82.jpg"},{"name":"83","url":"https://cdn.jsdelivr.net/gh/Dreamy-TZK/iemotion-pic@latest/img/猥琐萌/83.jpg"},{"name":"84","url":"https://cdn.jsdelivr.net/gh/Dreamy-TZK/iemotion-pic@latest/img/猥琐萌/84.jpg"},{"name":"85","url":"https://cdn.jsdelivr.net/gh/Dreamy-TZK/iemotion-pic@latest/img/猥琐萌/85.jpg"},{"name":"86","url":"https://cdn.jsdelivr.net/gh/Dreamy-TZK/iemotion-pic@latest/img/猥琐萌/86.jpg"},{"name":"87","url":"https://cdn.jsdelivr.net/gh/Dreamy-TZK/iemotion-pic@latest/img/猥琐萌/87.jpg"},{"name":"88","url":"https://cdn.jsdelivr.net/gh/Dreamy-TZK/iemotion-pic@latest/img/猥琐萌/88.jpg"},{"name":"89","url":"https://cdn.jsdelivr.net/gh/Dreamy-TZK/iemotion-pic@latest/img/猥琐萌/89.jpg"},{"name":"9","url":"https://cdn.jsdelivr.net/gh/Dreamy-TZK/iemotion-pic@latest/img/猥琐萌/9.jpg"},{"name":"90","url":"https://cdn.jsdelivr.net/gh/Dreamy-TZK/iemotion-pic@latest/img/猥琐萌/90.jpg"},{"name":"91","url":"https://cdn.jsdelivr.net/gh/Dreamy-TZK/iemotion-pic@latest/img/猥琐萌/91.jpg"},{"name":"92","url":"https://cdn.jsdelivr.net/gh/Dreamy-TZK/iemotion-pic@latest/img/猥琐萌/92.jpg"},{"name":"93","url":"https://cdn.jsdelivr.net/gh/Dreamy-TZK/iemotion-pic@latest/img/猥琐萌/93.jpg"},{"name":"94","url":"https://cdn.jsdelivr.net/gh/Dreamy-TZK/iemotion-pic@latest/img/猥琐萌/94.jpg"},{"name":"95","url":"https://cdn.jsdelivr.net/gh/Dreamy-TZK/iemotion-pic@latest/img/猥琐萌/95.jpg"},{"name":"96","url":"https://cdn.jsdelivr.net/gh/Dreamy-TZK/iemotion-pic@latest/img/猥琐萌/96.jpg"},{"name":"97","url":"https://cdn.jsdelivr.net/gh/Dreamy-TZK/iemotion-pic@latest/img/猥琐萌/97.jpg"},{"name":"98","url":"https://cdn.jsdelivr.net/gh/Dreamy-TZK/iemotion-pic@latest/img/猥琐萌/98.jpg"},{"name":"99","url":"https://cdn.jsdelivr.net/gh/Dreamy-TZK/iemotion-pic@latest/img/猥琐萌/99.jpg"}]}